pulse/__init__.py
pulse/config.py
pulse/consumer.py
pulse/producer.py
pulse/proto_manager.py
pulse/proto/__init__.py
pulse/proto/pulse_pb2.py
pulse/proto/pulse_pb2_grpc.py
tests/__init__.py
tests/test_pulse.py
pulse_broker-1.0.14.dist-info/METADATA
pulse_broker-1.0.14.dist-info/WHEEL
pulse_broker-1.0.14.dist-info/top_level.txt
pulse_broker-1.0.14.dist-info/RECORD
