Metadata-Version: 2.4
Name: pulse-broker
Version: 1.0.14
Summary: Python SDK for Pulse Broker
Home-page: https://github.com/marcosrosa/pulse
Author: Marcos Rosa
Author-email: marcos@example.com
Project-URL: Bug Tracker, https://github.com/marcosrosa/pulse/issues
Classifier: Programming Language :: Python :: 3
Classifier: License :: OSI Approved :: MIT License
Classifier: Operating System :: OS Independent
Requires-Python: >=3.7
Requires-Dist: grpcio>=1.50.0
Requires-Dist: protobuf>=4.21.0
Requires-Dist: pyyaml>=6.0
Dynamic: author
Dynamic: author-email
Dynamic: classifier
Dynamic: description
Dynamic: description-content-type
Dynamic: home-page
Dynamic: project-url
Dynamic: requires-dist
Dynamic: requires-python
Dynamic: summary
